php_app_lib_classifier/__init__.py
php_app_lib_classifier/analysis.py
php_app_lib_classifier/cli.py
php_app_lib_classifier/enums.py
php_app_lib_classifier/openapi_utils.py
php_app_lib_classifier/utils.py
php_app_lib_classifier/indicators/__init__.py
php_app_lib_classifier/indicators/base.py
php_app_lib_classifier/indicators/composer_require_instructions.py
php_app_lib_classifier/indicators/composer_type_library.py
php_app_lib_classifier/indicators/composer_type_project.py
php_app_lib_classifier/indicators/has_docker_config.py
php_app_lib_classifier/indicators/has_env_file.py
php_app_lib_classifier/indicators/has_framework_dirs.py
php_app_lib_classifier/indicators/has_frontend_assets.py
php_app_lib_classifier/indicators/has_htaccess.py
php_app_lib_classifier/indicators/has_psr4_autoload.py
php_app_lib_classifier/indicators/has_views_templates.py
php_app_lib_classifier/indicators/has_web_entry_point.py
php_app_lib_classifier/indicators/has_web_framework.py
php_app_lib_classifier/indicators/library_readme.py
php_app_lib_classifier/indicators/src_directory.py
php_app_lib_classifier/indicators/tests_directory.py
php_app_lib_classifier-0.1.3.dist-info/METADATA
php_app_lib_classifier-0.1.3.dist-info/WHEEL
php_app_lib_classifier-0.1.3.dist-info/entry_points.txt
php_app_lib_classifier-0.1.3.dist-info/RECORD
