Metadata-Version: 2.4
Name: php-app-lib-classifier
Version: 0.1.3
Summary: A modern, async PHP app library classifier.
Requires-Python: >=3.12
Requires-Dist: aiofiles>=24.1.0
Requires-Dist: httpx>=0.28.1
Requires-Dist: pydantic>=2.11.7
Requires-Dist: pyyaml>=6.0.2
Requires-Dist: rich>=14.0.0
Requires-Dist: structlog>=25.4.0
Requires-Dist: typer>=0.16.0
